[{"name": "Lv1", "title": "\uadf8\ub9b0\uac8c\uc774\ube14\uc988 \ube68\uac15\uba38\ub9ac \uc564 . 7 :, \ubb34\uc9c0\uac1c \uace8\uc9dc\uae30", "library": "\uac15\ub3d9\uad6c\ub9bd\uc131\ub0b4\ub3c4\uc11c\uad00", "in_date": "", "out_date": "2025.09.21", "status": "\ubc18\ub0a9\uc5f0\uae30"}, {"name": "Lv1", "title": "\uadf8\ub9b0\uac8c\uc774\ube14\uc988 \ube68\uac15\uba38\ub9ac \uc564 . 8 :, \uc544\ub4e4\ub4e4 \ub538\ub4e4", "library": "\uac15\ub3d9\uad6c\ub9bd\uc131\ub0b4\ub3c4\uc11c\uad00", "in_date": "", "out_date": "2025.09.21", "status": "\ubc18\ub0a9\uc5f0\uae30"}, {"name": "Lv1", "title": "\uadf8\ub9b0\uac8c\uc774\ube14\uc988 \ube68\uac15\uba38\ub9ac \uc564 . 9 :, \ub2ec\uc774\uac00\uace0 \ud574\uac00\uac00\uace0", "library": "\uac15\ub3d9\uad6c\ub9bd\uc131\ub0b4\ub3c4\uc11c\uad00", "in_date": "", "out_date": "2025.09.21", "status": "\ubc18\ub0a9\uc5f0\uae30"}, {"name": "Lv1", "title": "\uc138\uc0c1\uc5d0 \ub300\ud558\uc5ec \uc6b0\ub9ac\uac00 \ub354 \uc798 \uc54c\uc544\uc57c \ud560 \uad50\uc591. 41, \ube45\ub370\uc774\ud130 \ube45\ube0c\ub7ec\ub354\uac00 \uc544\ub2d0\uae4c?", "library": "\uac15\ub3d9\uad6c\ub9bd\ucc9c\ud638\ub3c4\uc11c\uad00", "in_date": "", "out_date": "2025.09.14", "status": "\ubc18\ub0a9\uc5f0\uae30"}, {"name": "Lv1", "title": "\uc138\uc0c1\uc5d0 \ub300\ud558\uc5ec \uc6b0\ub9ac\uac00 \ub354 \uc798 \uc54c\uc544\uc57c \ud560 \uad50\uc591. 47, \uc800\uc791\uad8c, \uce74\ud53c\ub77c\uc774\ud2b8\ub0d0? \uce74\ud53c\ub808\ud504\ud2b8\ub0d0?", "library": "\uac15\ub3d9\uad6c\ub9bd\ucc9c\ud638\ub3c4\uc11c\uad00", "in_date": "", "out_date": "2025.09.14", "status": "\ubc18\ub0a9\uc5f0\uae30"}, {"name": "Lv1", "title": "\uc138\uc0c1\uc5d0 \ub300\ud558\uc5ec \uc6b0\ub9ac\uac00 \ub354 \uc798 \uc54c\uc544\uc57c \ud560 \uad50\uc591. 37, \uc2a4\ud3ec\uce20 \uc724\ub9ac, \uc2b9\ub9ac \uc9c0\uc0c1\uc8fc\uc758\uc758 \ud0c0\uac1c\ucc45\uc77c\uae4c?", "library": "\uac15\ub3d9\uad6c\ub9bd\ucc9c\ud638\ub3c4\uc11c\uad00", "in_date": "", "out_date": "2025.09.14", "status": "\ubc18\ub0a9\uc5f0\uae30"}, {"name": "Lv1", "title": "\uc138\uc0c1\uc5d0 \ub300\ud558\uc5ec \uc6b0\ub9ac\uac00 \ub354 \uc798 \uc54c\uc544\uc57c \ud560 \uad50\uc591. 43, \uc81c\ub178\uc0ac\uc774\ub4dc, \uc9d1\ub2e8 \ud559\uc0b4\uc740 \uc65c \ubc18\ubcf5\ub420\uae4c?", "library": "\uac15\ub3d9\uad6c\ub9bd\ucc9c\ud638\ub3c4\uc11c\uad00", "in_date": "", "out_date": "2025.09.14", "status": "\ubc18\ub0a9\uc5f0\uae30"}, {"name": "Lv1", "title": "\uc138\uc0c1\uc5d0 \ub300\ud558\uc5ec \uc6b0\ub9ac\uac00 \ub354 \uc798 \uc54c\uc544\uc57c \ud560 \uad50\uc591. 67, \uc6b0\uc8fc\uac1c\ubc1c \uc6b0\uc8fc \ubd88\ud3c9\ub4f1\uc744 \ucd08\ub798\ud560\uae4c?", "library": "\uac15\ub3d9\uad6c\ub9bd\ucc9c\ud638\ub3c4\uc11c\uad00", "in_date": "", "out_date": "2025.09.14", "status": "\ubc18\ub0a9\uc5f0\uae30"}, {"name": "Lv1", "title": "\uc138\uc0c1\uc5d0 \ub300\ud558\uc5ec \uc6b0\ub9ac\uac00 \ub354 \uc798 \uc54c\uc544\uc57c \ud560 \uad50\uc591. 58, \uc2a4\ud06c\ub9b0 \ub3c5\uacfc\uc810, \ucd95\ubcf5\uc778\uac00? \ub3c5\uc778\uac00?", "library": "\uac15\ub3d9\uad6c\ub9bd\ucc9c\ud638\ub3c4\uc11c\uad00", "in_date": "", "out_date": "2025.09.14", "status": "\ubc18\ub0a9\uc5f0\uae30"}, {"name": "Lv1", "title": "\uc218\uc601 \ub9c8\uc2a4\ud130 \uac00\uc774\ub4dc = Swimming master guide", "library": "\uac15\ub3d9\uad6c\ub9bd\uac15\uc77c\ub3c4\uc11c\uad00", "in_date": "", "out_date": "2025.09.06", "status": "\ub300\ucd9c"}, {"name": "Lv1", "title": "(\ub9cc\ud654\ub85c \ubcf4\ub294)3\ubd84 \ucca0\ud559. 3, \uc11c\uc591 \ud604\ub300 \ucca0\ud559\ud3b8", "library": "\uac15\ub3d9\uad6c\ub9bd\ud574\uacf5\ub3c4\uc11c\uad00", "in_date": "", "out_date": "2025.09.13", "status": "\ubc18\ub0a9\uc5f0\uae30"}, {"name": "Lv1", "title": "\uadf8\ub9b0\uac8c\uc774\ube14\uc988 \ube68\uac15\uba38\ub9ac \uc564. 3 : \uccab\uc0ac\ub791", "library": "\uac15\ub3d9\uad6c\ub9bd\ud574\uacf5\ub3c4\uc11c\uad00", "in_date": "", "out_date": "2025.09.13", "status": "\ubc18\ub0a9\uc5f0\uae30"}, {"name": "Lv1", "title": "\uadf8\ub9b0\uac8c\uc774\ube14\uc988 \ube68\uac15\uba38\ub9ac \uc564. 4 : \uc57d\uc18d", "library": "\uac15\ub3d9\uad6c\ub9bd\ud574\uacf5\ub3c4\uc11c\uad00", "in_date": "", "out_date": "2025.09.13", "status": "\ubc18\ub0a9\uc5f0\uae30"}, {"name": "Lv1", "title": "\uadf8\ub9b0\uac8c\uc774\ube14\uc988 \ube68\uac15\uba38\ub9ac \uc564. 5 : \uc6e8\ub529\ub4dc\ub808\uc2a4", "library": "\uac15\ub3d9\uad6c\ub9bd\ud574\uacf5\ub3c4\uc11c\uad00", "in_date": "", "out_date": "2025.09.13", "status": "\ubc18\ub0a9\uc5f0\uae30"}, {"name": "Lv1", "title": "\uacf0\ud321\uc774 \uc218\uc9c0 : \uacf0\ud321\uc774\uc758 \uac70\uc758 \ubaa8\ub4e0 \uac83", "library": "\uac15\ub3d9\uad6c\ub9bd\uc131\ub0b4\ub3c4\uc11c\uad00", "in_date": "", "out_date": "2025.09.07", "status": "\ubc18\ub0a9\uc5f0\uae30"}, {"name": "Lv1", "title": "\uadf8\ub9b0\uac8c\uc774\ube14\uc988 \ube68\uac15\uba38\ub9ac \uc564 . 6 :, \ud589\ubcf5\ud55c \ub098\ub0a0", "library": "\uac15\ub3d9\uad6c\ub9bd\uc131\ub0b4\ub3c4\uc11c\uad00", "in_date": "", "out_date": "2025.09.07", "status": "\ubc18\ub0a9\uc5f0\uae30"}, {"name": "Lv1", "title": "\ucc45\uc774 \uc88b\uc740 \uac78 \uc5b4\ub5a1\ud574", "library": "\uac15\ub3d9\uad6c\ub9bd\uc131\ub0b4\ub3c4\uc11c\uad00", "in_date": "", "out_date": "2025.09.07", "status": "\ubc18\ub0a9\uc5f0\uae30"}, {"name": "Lv1", "title": "(\ubcc4\ub625\ubcc4 \uc544\uc90c\ub9c8\uac00 \ub4e4\ub824\uc8fc\ub294) \uc6b0\uc8fc \uc774\uc57c\uae30", "library": "\uac15\ub3d9\uad6c\ub9bd\uc131\ub0b4\ub3c4\uc11c\uad00", "in_date": "", "out_date": "2025.09.07", "status": "\ubc18\ub0a9\uc5f0\uae30"}, {"name": "Lv2", "title": "\ubc8c\uac70\ubc97\uc740 \ud55c\uad6d\uc0ac : \uc778\ubb3c\ud3b8", "library": "\uac15\ub3d9\uad6c\ub9bd\uc131\ub0b4\ub3c4\uc11c\uad00", "in_date": "", "out_date": "2025.09.21", "status": "\ubc18\ub0a9\uc5f0\uae30"}, {"name": "Lv2", "title": "\uadf8\ub9b0\uac8c\uc774\ube14\uc988 \ube68\uac15\uba38\ub9ac \uc564 . 10 :, \uc5b8\uc81c\uae4c\uc9c0\ub098", "library": "\uac15\ub3d9\uad6c\ub9bd\uc131\ub0b4\ub3c4\uc11c\uad00", "in_date": "", "out_date": "2025.09.21", "status": "\ubc18\ub0a9\uc5f0\uae30"}, {"name": "Lv2", "title": "\ud53c\ub77c\ub2c8\uc544 \uc774\uc57c\uae30", "library": "\uac15\ub3d9\uad6c\ub9bd\uc131\ub0b4\ub3c4\uc11c\uad00", "in_date": "", "out_date": "2025.09.21", "status": "\ubc18\ub0a9\uc5f0\uae30"}, {"name": "Lv2", "title": "\uc138\uc0c1\uc5d0 \ub300\ud558\uc5ec \uc6b0\ub9ac\uac00 \ub354 \uc798 \uc54c\uc544\uc57c \ud560 \uad50\uc591. 40, \uc0b0\uc5c5\ud615 \ub18d\uc5c5", "library": "\uac15\ub3d9\uad6c\ub9bd\ucc9c\ud638\ub3c4\uc11c\uad00", "in_date": "", "out_date": "2025.09.14", "status": "\ubc18\ub0a9\uc5f0\uae30"}, {"name": "Lv2", "title": "\ud30c\ub77c\uc624\uc640 \uc774\uc9d1\ud2b8", "library": "\uac15\ub3d9\uad6c\ub9bd\ucc9c\ud638\ub3c4\uc11c\uad00", "in_date": "", "out_date": "2025.09.14", "status": "\ubc18\ub0a9\uc5f0\uae30"}, {"name": "Lv2", "title": "\ucc9c\ub465\uc544, \ub0b4 \uc678\uce68\uc744 \ub4e4\uc5b4\ub77c!", "library": "\uac15\ub3d9\uad6c\ub9bd\ucc9c\ud638\ub3c4\uc11c\uad00", "in_date": "", "out_date": "2025.09.14", "status": "\ubc18\ub0a9\uc5f0\uae30"}, {"name": "Lv2", "title": "\uc124\ubbfc\uc11d\uc758 \uc870\uc120\uc655\uc870\uc2e4\ub85d : \ub300\ud55c\ubbfc\uad6d\uc774 \uc120\ud0dd\ud55c \uc5ed\uc0ac \uc774\uc57c\uae30", "library": "\uac15\ub3d9\uad6c\ub9bd\ucc9c\ud638\ub3c4\uc11c\uad00", "in_date": "", "out_date": "2025.09.14", "status": "\ubc18\ub0a9\uc5f0\uae30"}, {"name": "Lv2", "title": "\uccad\uad50\ub3c4 \ud601\uba85\uacfc \uba85\uc608\ud601\uba85", "library": "\uac15\ub3d9\uad6c\ub9bd\ucc9c\ud638\ub3c4\uc11c\uad00", "in_date": "", "out_date": "2025.09.14", "status": "\ubc18\ub0a9\uc5f0\uae30"}, {"name": "Lv2", "title": "\ub8e8\ud130\uc640 \uc885\uad50\uac1c\ud601", "library": "\uac15\ub3d9\uad6c\ub9bd\ucc9c\ud638\ub3c4\uc11c\uad00", "in_date": "", "out_date": "2025.09.14", "status": "\ubc18\ub0a9\uc5f0\uae30"}, {"name": "Lv2", "title": "\ud3f0\ub354 \uc528\uc758 \uc704\ub300\ud55c \ud558\ub8e8 : \ud55c \uc0ac\ub78c\uc758 \uc778\uc0dd\uc744 \ubc14\uafbc 7\uac00\uc9c0 \uc120\ubb3c \uc774\uc57c\uae30", "library": "\uac15\ub3d9\uad6c\ub9bd\ud574\uacf5\ub3c4\uc11c\uad00", "in_date": "", "out_date": "2025.09.13", "status": "\ubc18\ub0a9\uc5f0\uae30"}, {"name": "Lv2", "title": "(\uc774\uc9c0\uc131\uc758)1\ub9cc \ud0ac\ub85c\ubbf8\ud130 : \uadf8\ub4e4\uc740 \uc65c \ubaa9\uc228\uc744 \uac74 \uc5ec\uc815\uc744 \ub5a0\ub098\ub294\uac00?", "library": "\uac15\ub3d9\uad6c\ub9bd\ud574\uacf5\ub3c4\uc11c\uad00", "in_date": "", "out_date": "2025.09.13", "status": "\ubc18\ub0a9\uc5f0\uae30"}, {"name": "Lv2", "title": "9\ub4f1\uae09 \uaf34\ucc0c, 1\ub144 \ub9cc\uc5d0 \ud1b5\uc5ed\uc0ac \ub41c \ube44\ubc95", "library": "\uac15\ub3d9\uad6c\ub9bd\ud574\uacf5\ub3c4\uc11c\uad00", "in_date": "", "out_date": "2025.09.13", "status": "\ubc18\ub0a9\uc5f0\uae30"}, {"name": "Lv2", "title": "\uc138\uacc4 \uba85\ubb38\uac00\uc758 \ub3c5\uc11c\uad50\uc721", "library": "\uac15\ub3d9\uad6c\ub9bd\ud574\uacf5\ub3c4\uc11c\uad00", "in_date": "", "out_date": "2025.09.13", "status": "\ubc18\ub0a9\uc5f0\uae30"}, {"name": "Lv2", "title": "\ubd88\uaf43 \uc218\uc601 \ub300\ud68c", "library": "\uac15\ub3d9\uad6c\ub9bd\ud574\uacf5\ub3c4\uc11c\uad00", "in_date": "", "out_date": "2025.09.06", "status": "\ubc18\ub0a9\uc5f0\uae30"}, {"name": "Lv3", "title": "\ubc18\uc9c0\uc758 \uc81c\uc655. 1, \ubc18\uc9c0\uc6d0\uc815\ub300 1", "library": "\uac15\ub3d9\uad6c\ub9bd\ucc9c\ud638\ub3c4\uc11c\uad00", "in_date": "", "out_date": "2025.09.14", "status": "\ubc18\ub0a9\uc5f0\uae30"}, {"name": "Lv3", "title": "(\uc0dd\uac01\uc774 \ud0c1 \ud2b8\uc774\ub294)5\ubd84 \uba85\uc791\ub3d9\ud654", "library": "\uac15\ub3d9\uad6c\ub9bd\ucc9c\ud638\ub3c4\uc11c\uad00", "in_date": "", "out_date": "2025.09.14", "status": "\ubc18\ub0a9\uc5f0\uae30"}, {"name": "Lv3", "title": "(\uc778\uc131 \ubc1c\ub2ec\uc744 \ub3d5\ub294)\ub9c8\uc74c \uc131\uc7a5 \ub3d9\ud654", "library": "\uac15\ub3d9\uad6c\ub9bd\ucc9c\ud638\ub3c4\uc11c\uad00", "in_date": "", "out_date": "2025.09.14", "status": "\ubc18\ub0a9\uc5f0\uae30"}, {"name": "Lv3", "title": "(\uc704\ub300\ud55c \ud0d0\uc815 \ub124\uc774\ud2b8) \uc0ac\ub77c\uc9c4 \uae61\ud1b5\uc744 \ucc3e\uc544\uc11c", "library": "\uac15\ub3d9\uad6c\ub9bd\ucc9c\ud638\ub3c4\uc11c\uad00", "in_date": "", "out_date": "2025.09.14", "status": "\ubc18\ub0a9\uc5f0\uae30"}, {"name": "Lv3", "title": "(\uad50\uc591 \uc788\ub294 \uc6b0\ub9ac \uc544\uc774\ub97c \uc704\ud55c) \uc138\uacc4 \uc5ed\uc0ac \uc774\uc57c\uae30. 4, \ud604\ub300\ud3b8 \uc0c1", "library": "\uac15\ub3d9\uad6c\ub9bd\ucc9c\ud638\ub3c4\uc11c\uad00", "in_date": "", "out_date": "2025.09.14", "status": "\ubc18\ub0a9\uc5f0\uae30"}, {"name": "Lv3", "title": "(\uad50\uc591 \uc788\ub294 \uc6b0\ub9ac \uc544\uc774\ub97c \uc704\ud55c) \uc138\uacc4 \uc5ed\uc0ac \uc774\uc57c\uae30. 5, \ud604\ub300\ud3b8 \ud558", "library": "\uac15\ub3d9\uad6c\ub9bd\ucc9c\ud638\ub3c4\uc11c\uad00", "in_date": "", "out_date": "2025.09.14", "status": "\ubc18\ub0a9\uc5f0\uae30"}, {"name": "Lv3", "title": "(\uad50\uc591 \uc788\ub294 \uc6b0\ub9ac \uc544\uc774\ub97c \uc704\ud55c) \uc138\uacc4 \uc5ed\uc0ac \uc774\uc57c\uae30. 3, \uadfc\ub300\ud3b8", "library": "\uac15\ub3d9\uad6c\ub9bd\ucc9c\ud638\ub3c4\uc11c\uad00", "in_date": "", "out_date": "2025.09.14", "status": "\ubc18\ub0a9\uc5f0\uae30"}, {"name": "Lv3", "title": "\ubc1c\ub05d \uc6b0\ubb3c\ucb48\ubb3c", "library": "\uac15\ub3d9\uad6c\ub9bd\ucc9c\ud638\ub3c4\uc11c\uad00", "in_date": "", "out_date": "2025.09.14", "status": "\ubc18\ub0a9\uc5f0\uae30"}, {"name": "Lv3", "title": "\uc608\ubed0\uc9c0\ub294 \uc57d\uacfc \ubcf4\uac74 \uc120\uc0dd\ub2d8", "library": "\uac15\ub3d9\uad6c\ub9bd\ucc9c\ud638\ub3c4\uc11c\uad00", "in_date": "", "out_date": "2025.09.14", "status": "\ubc18\ub0a9\uc5f0\uae30"}, {"name": "Lv3", "title": "\uacfc\ud559\uacf5\ud654\uad6d \uc218\ud559\ubc95\uc815. 5, \ud655\ub960\uacfc \ud1b5\uacc4", "library": "\uac15\ub3d9\uad6c\ub9bd\ucc9c\ud638\ub3c4\uc11c\uad00", "in_date": "", "out_date": "2025.09.14", "status": "\ubc18\ub0a9\uc5f0\uae30"}, {"name": "Lv3", "title": "\uc774\uc0c1\ud55c \ub098\ub77c\uc758 \ud770\ud1a0\ub07c \ubd80\uc778", "library": "\uac15\ub3d9\uad6c\ub9bd\ucc9c\ud638\ub3c4\uc11c\uad00", "in_date": "", "out_date": "2025.09.14", "status": "\ubc18\ub0a9\uc5f0\uae30"}, {"name": "Lv3", "title": "\ubc18\ub3c4\uccb4\uac00 \uadf8\ub807\uac8c \uc911\uc694\ud55c\uac00\uc694? : \ub9fa\uace0 \ub04a\ub294 \uae30\ub9c9\ud78c \ub2a5\ub825\uc73c\ub85c \ub098\uc758 \uc77c\uc0c1\uacfc \uc138\uacc4\ub97c \uc950\ub77d\ud3b4\ub77d\ud558\ub294 \uc791\ub514\uc791\uc740 \ubc18\ub3c4\uccb4 \uc774\uc57c\uae30", "library": "\uac15\ub3d9\uad6c\ub9bd\ub454\ucd0c\ub3c4\uc11c\uad00", "in_date": "", "out_date": "2025.09.06", "status": "\ub300\ucd9c"}, {"name": "Lv3", "title": "\ucc44\uc18c \ud559\uad50\uc640 \uc7a0\uafb8\ub7ec\uae30 \ud53c\ub9dd", "library": "\uac15\ub3d9\uad6c\ub9bd\ud574\uacf5\ub3c4\uc11c\uad00", "in_date": "", "out_date": "2025.09.13", "status": "\ubc18\ub0a9\uc5f0\uae30"}, {"name": "Lv3", "title": "\ub3c8\ud0a4\ud638\ud14c", "library": "\uac15\ub3d9\uad6c\ub9bd\ud574\uacf5\ub3c4\uc11c\uad00", "in_date": "", "out_date": "2025.09.13", "status": "\ubc18\ub0a9\uc5f0\uae30"}, {"name": "Lv3", "title": "\ucc9c\uc5f0\ub2f9 \uc0ac\uc9c4\uad00", "library": "\uac15\ub3d9\uad6c\ub9bd\uac15\uc77c\ub3c4\uc11c\uad00", "in_date": "", "out_date": "2025.09.06", "status": "\ub300\ucd9c"}, {"name": "Lv3", "title": "\ubcc4\uc744 \uc0ac\ub791\ud558\ub294 \uc544\uc774\ub4e4\uc544 : \uc724\ub3d9\uc8fc \ub3d9\uc2dc\uc9d1", "library": "\uac15\ub3d9\uad6c\ub9bd\ud574\uacf5\ub3c4\uc11c\uad00", "in_date": "", "out_date": "2025.09.13", "status": "\ubc18\ub0a9\uc5f0\uae30"}, {"name": "Lv3", "title": "\ubaa8\ud0b9\uc81c\uc774", "library": "\uac15\ub3d9\uad6c\ub9bd\uc131\ub0b4\ub3c4\uc11c\uad00", "in_date": "", "out_date": "2025.09.07", "status": "\ubc18\ub0a9\uc5f0\uae30"}, {"name": "Lv3", "title": "\ucea3\uce6d\ud30c\uc774\uc5b4", "library": "\uac15\ub3d9\uad6c\ub9bd\uc131\ub0b4\ub3c4\uc11c\uad00", "in_date": "", "out_date": "2025.09.07", "status": "\ubc18\ub0a9\uc5f0\uae30"}, {"name": "Lv3", "title": "(\ubcc4\ub625\ubcc4 \uc544\uc90c\ub9c8\uac00 \ub4e4\ub824\uc8fc\ub294)\ud654\uc0b0 \uc774\uc57c\uae30", "library": "\uac15\ub3d9\uad6c\ub9bd\uc131\ub0b4\ub3c4\uc11c\uad00", "in_date": "", "out_date": "2025.09.07", "status": "\ubc18\ub0a9\uc5f0\uae30"}, {"name": "Lv3", "title": "(\uc11c\uc6b8\ub300 \uad50\uc218\uc640 \ud568\uaed8\ud558\ub294)10\ub300\ub97c \uc704\ud55c \uad50\uc591 \uc218\uc5c5. 7, \ud64d\uc131\uc6b1 \uad50\uc218\ub2d8\uc774 \ub4e4\ub824\uc8fc\ub294 \uacfc\ud559\uae30\uc220\ud559 \uc774\uc57c\uae30", "library": "\uac15\ub3d9\uad6c\ub9bd\uc131\ub0b4\ub3c4\uc11c\uad00", "in_date": "", "out_date": "2025.09.07", "status": "\ubc18\ub0a9\uc5f0\uae30"}, {"name": "Lv4", "title": "(\ubf40\ub871\ubf40\ub871 \ubf40\ub85c\ub85c)\ub098\ub3c4 \ubcd1\uc6d0\uc5d0 \uac08 \uc218 \uc788\uc5b4! : \ubf40\ub85c\ub85c \ubcd1\uc6d0\ub180\uc774", "library": "\uac15\ub3d9\uad6c\ub9bd\uc131\ub0b4\ub3c4\uc11c\uad00", "in_date": "", "out_date": "2025.09.21", "status": "\ubc18\ub0a9\uc5f0\uae30"}, {"name": "Lv4", "title": "(\ubf40\ub871\ubf40\ub871 \ubf40\ub85c\ub85c)\ubf40\ub871\ubf40\ub871 \uad6c\ucd9c \uc791\uc804", "library": "\uac15\ub3d9\uad6c\ub9bd\uc131\ub0b4\ub3c4\uc11c\uad00", "in_date": "", "out_date": "2025.09.21", "status": "\ubc18\ub0a9\uc5f0\uae30"}, {"name": "Lv4", "title": "\uc81c\ub77c\ub284\uacfc \uc624\ud6c4\uc758 \uaf43\uc7a0", "library": "\uac15\ub3d9\uad6c\ub9bd\uc131\ub0b4\ub3c4\uc11c\uad00", "in_date": "", "out_date": "2025.09.21", "status": "\ubc18\ub0a9\uc5f0\uae30"}, {"name": "Lv4", "title": "\uc624\uc18c\ub9ac\uc758 \uc774\ubcc4 \uc120\ubb3c", "library": "\uac15\ub3d9\uad6c\ub9bd\uc131\ub0b4\ub3c4\uc11c\uad00", "in_date": "", "out_date": "2025.09.21", "status": "\ubc18\ub0a9\uc5f0\uae30"}, {"name": "Lv4", "title": "\ud0dc\ud48d\uc774 \uc624\ub294 \ub0a0", "library": "\uac15\ub3d9\uad6c\ub9bd\uc131\ub0b4\ub3c4\uc11c\uad00", "in_date": "", "out_date": "2025.09.21", "status": "\ubc18\ub0a9\uc5f0\uae30"}, {"name": "Lv4", "title": "\uae4c\ub9c8\uadc0 \ubaa8\ud2f0\uba38 \uae38\ub4e4\uc774\uae30", "library": "\uac15\ub3d9\uad6c\ub9bd\uc131\ub0b4\ub3c4\uc11c\uad00", "in_date": "", "out_date": "2025.09.21", "status": "\ubc18\ub0a9\uc5f0\uae30"}, {"name": "Lv4", "title": "\uacf5\ub8e1\uc12c\uc5d0 \uac04 \ud0c0\uc694", "library": "\uac15\ub3d9\uad6c\ub9bd\uc131\ub0b4\ub3c4\uc11c\uad00", "in_date": "", "out_date": "2025.09.21", "status": "\ubc18\ub0a9\uc5f0\uae30"}, {"name": "Lv4", "title": "\uc5c9\ub369\uc774 \ud0d0\uc815. 7, \ubfe1\ubfe1 \uaca8\uc6b8 \uc0b0\uc758 \ud558\uc580 \uad34\ubb3c!?", "library": "\uac15\ub3d9\uad6c\ub9bd\uc131\ub0b4\ub3c4\uc11c\uad00", "in_date": "", "out_date": "2025.09.21", "status": "\ubc18\ub0a9\uc5f0\uae30"}, {"name": "Lv4", "title": "(\ubf40\ub871\ubf40\ub871 \ubf40\ub85c\ub85c)\uc6b0\ub2f9\ud0d5\ud0d5 \ud558\ub8e8", "library": "\uac15\ub3d9\uad6c\ub9bd\uc131\ub0b4\ub3c4\uc11c\uad00", "in_date": "", "out_date": "2025.09.07", "status": "\ubc18\ub0a9\uc5f0\uae30"}, {"name": "Lv4", "title": "(\ubf40\ub871\ubf40\ub871 \ubf40\ub85c\ub85c)\uc751\uac00\ud560 \uc2dc\uac04\uc774\uc57c, \ud06c\ub871!", "library": "\uac15\ub3d9\uad6c\ub9bd\uc131\ub0b4\ub3c4\uc11c\uad00", "in_date": "", "out_date": "2025.09.07", "status": "\ubc18\ub0a9\uc5f0\uae30"}, {"name": "Lv4", "title": "See, touch, feel ABC", "library": "\uac15\ub3d9\uad6c\ub9bd\uc131\ub0b4\ub3c4\uc11c\uad00", "in_date": "", "out_date": "2025.09.07", "status": "\ubc18\ub0a9\uc5f0\uae30"}, {"name": "Lv4", "title": "\ubf40\ub85c\ub85c\uc758 \uaf80\ubcd1", "library": "\uac15\ub3d9\uad6c\ub9bd\uc131\ub0b4\ub3c4\uc11c\uad00", "in_date": "", "out_date": "2025.09.07", "status": "\ubc18\ub0a9\uc5f0\uae30"}, {"name": "Lv5", "title": "(\uc544\ub984\ub2e4\uc6b4 \uc544\uc774) \uc0ec\ub86f \uc774\uc57c\uae30", "library": "\uac15\ub3d9\uad6c\ub9bd\uc131\ub0b4\ub3c4\uc11c\uad00", "in_date": "", "out_date": "2025.09.21", "status": "\ubc18\ub0a9\uc5f0\uae30"}, {"name": "Lv5", "title": "\ub458\uc774 \uaf2d \ub2ee\uc558\ub124!", "library": "\uac15\ub3d9\uad6c\ub9bd\uc131\ub0b4\ub3c4\uc11c\uad00", "in_date": "", "out_date": "2025.09.21", "status": "\ubc18\ub0a9\uc5f0\uae30"}, {"name": "Lv5", "title": "\ud669\uae08 \uace0\ub77c\ub2c8", "library": "\uac15\ub3d9\uad6c\ub9bd\uc131\ub0b4\ub3c4\uc11c\uad00", "in_date": "", "out_date": "2025.09.21", "status": "\ubc18\ub0a9\uc5f0\uae30"}, {"name": "Lv5", "title": "\ub5bc\uad74\ub5bc\uad74 \uc0ac\ub974\ub974 \uc0ac\ub974\ub974", "library": "\uac15\ub3d9\uad6c\ub9bd\uc131\ub0b4\ub3c4\uc11c\uad00", "in_date": "", "out_date": "2025.09.21", "status": "\ubc18\ub0a9\uc5f0\uae30"}, {"name": "Lv5", "title": "\uc624\uc9c1 \ud558\ub098\ubfd0\uc778", "library": "\uac15\ub3d9\uad6c\ub9bd\uc131\ub0b4\ub3c4\uc11c\uad00", "in_date": "", "out_date": "2025.09.21", "status": "\ubc18\ub0a9\uc5f0\uae30"}, {"name": "Lv5", "title": "\uc2e0\ube44\ud55c \ube44\ubc00 \ud1b5\ub85c", "library": "\uac15\ub3d9\uad6c\ub9bd\uc131\ub0b4\ub3c4\uc11c\uad00", "in_date": "", "out_date": "2025.09.21", "status": "\ubc18\ub0a9\uc5f0\uae30"}, {"name": "Lv5", "title": "\uc5d0\uc774\uc2a4 \uae40\uc900\uc218", "library": "\uac15\ub3d9\uad6c\ub9bd\uc131\ub0b4\ub3c4\uc11c\uad00", "in_date": "", "out_date": "2025.09.21", "status": "\ubc18\ub0a9\uc5f0\uae30"}, {"name": "Lv5", "title": "(\ud37c\uc2a4\ud2b8 \ub808\uc774\ub514) \ubbf8\uc178 \uc624\ubc14\ub9c8 : \ubcc0\ud654\uc640 \uc0ac\ub791\uc758 \uba54\uc2dc\uc9c0\ub97c \uc804\ud558\ub2e4", "library": "\uac15\ub3d9\uad6c\ub9bd\ucc9c\ud638\ub3c4\uc11c\uad00", "in_date": "", "out_date": "2025.09.14", "status": "\ubc18\ub0a9\uc5f0\uae30"}, {"name": "Lv5", "title": "\ubc14\ud034\uac00 \uac16\uace0 \uc2f6\uc5b4!", "library": "\uac15\ub3d9\uad6c\ub9bd\ucc9c\ud638\ub3c4\uc11c\uad00", "in_date": "", "out_date": "2025.09.14", "status": "\ubc18\ub0a9\uc5f0\uae30"}, {"name": "Lv5", "title": "\ub85c\uc790 \ud30c\ud06c\uc2a4", "library": "\uac15\ub3d9\uad6c\ub9bd\ucc9c\ud638\ub3c4\uc11c\uad00", "in_date": "", "out_date": "2025.09.14", "status": "\ubc18\ub0a9\uc5f0\uae30"}, {"name": "Lv5", "title": "\uc5d0\uba40\ub9b0 \ud33d\ud06c\ud5c8\uc2a4\ud2b8", "library": "\uac15\ub3d9\uad6c\ub9bd\ucc9c\ud638\ub3c4\uc11c\uad00", "in_date": "", "out_date": "2025.09.14", "status": "\ubc18\ub0a9\uc5f0\uae30"}, {"name": "Lv5", "title": "\uac1c\uad6c\ub9ac \ud55c \ub9c8\ub9ac\uac00", "library": "\uac15\ub3d9\uad6c\ub9bd\ucc9c\ud638\ub3c4\uc11c\uad00", "in_date": "", "out_date": "2025.09.14", "status": "\ubc18\ub0a9\uc5f0\uae30"}, {"name": "Lv5", "title": "\uc544\uae30 \uace0\ub798 \ud55c \ub9c8\ub9ac\uac00", "library": "\uac15\ub3d9\uad6c\ub9bd\ucc9c\ud638\ub3c4\uc11c\uad00", "in_date": "", "out_date": "2025.09.14", "status": "\ubc18\ub0a9\uc5f0\uae30"}, {"name": "Lv5", "title": "\uc560\ubc8c\ub808 \ud55c \ub9c8\ub9ac\uac00", "library": "\uac15\ub3d9\uad6c\ub9bd\ucc9c\ud638\ub3c4\uc11c\uad00", "in_date": "", "out_date": "2025.09.14", "status": "\ubc18\ub0a9\uc5f0\uae30"}, {"name": "Lv5", "title": "\uc6b0\uc801\uc6b0\uc801 \uba39\uc73c\uba74 \uc544\uc8fc \ub9db\uc788\uaca0\ub2e4", "library": "\uac15\ub3d9\uad6c\ub9bd\ucc9c\ud638\ub3c4\uc11c\uad00", "in_date": "", "out_date": "2025.09.14", "status": "\ubc18\ub0a9\uc5f0\uae30"}, {"name": "Lv5", "title": "\uac10\uae30 \uac78\ub9b0 \ubb3c\uace0\uae30 : \ubc15\uc815\uc12d \uadf8\ub9bc\ucc45", "library": "\uac15\ub3d9\uad6c\ub9bd\ucc9c\ud638\ub3c4\uc11c\uad00", "in_date": "", "out_date": "2025.09.14", "status": "\ubc18\ub0a9\uc5f0\uae30"}, {"name": "Lv5", "title": "\uacb0\ubc31", "library": "\uac15\ub3d9\uad6c\ub9bd\ud574\uacf5\ub3c4\uc11c\uad00", "in_date": "", "out_date": "2025.09.13", "status": "\ubc18\ub0a9\uc5f0\uae30"}, {"name": "Lv5", "title": "(\uc0dd\uc5b4\uac00 \ub4e4\ub824\uc8fc\ub294)\uc778\uc290\ub9b0 \uc774\uc57c\uae30", "library": "\uac15\ub3d9\uad6c\ub9bd\ud574\uacf5\ub3c4\uc11c\uad00", "in_date": "", "out_date": "2025.09.13", "status": "\ubc18\ub0a9\uc5f0\uae30"}, {"name": "Lv5", "title": "\ubcc0\ud638\uc0ac \uc5b4\ubca4\uc800\uc2a4. 2, \ub3d9\ubb3c \ubcf4\ud638\ubc95, \ucc45\uc784\uac10\uc744 \uac00\uc838\ub77c!", "library": "\uac15\ub3d9\uad6c\ub9bd\ud574\uacf5\ub3c4\uc11c\uad00", "in_date": "", "out_date": "2025.09.13", "status": "\ubc18\ub0a9\uc5f0\uae30"}, {"name": "Lv5", "title": "\uadf8\ub9ac\uc6b4 \uba54\uc774 \uc544\uc90c\ub9c8", "library": "\uac15\ub3d9\uad6c\ub9bd\ud574\uacf5\ub3c4\uc11c\uad00", "in_date": "", "out_date": "2025.09.13", "status": "\ubc18\ub0a9\uc5f0\uae30"}, {"name": "Lv5", "title": "\ud0a4\ub77c\uc758 \ubc15\ubb3c\uad00 \uc5ec\ud589. 8, \uc608\ub974\ubbf8\ud0c0\uc2dc \ubbf8\uc220\uad00", "library": "\uac15\ub3d9\uad6c\ub9bd\ud574\uacf5\ub3c4\uc11c\uad00", "in_date": "", "out_date": "2025.09.13", "status": "\ubc18\ub0a9\uc5f0\uae30"}, {"name": "Lv5", "title": "\uc288\ub809!", "library": "\uac15\ub3d9\uad6c\ub9bd\ud574\uacf5\ub3c4\uc11c\uad00", "in_date": "", "out_date": "2025.09.13", "status": "\ubc18\ub0a9\uc5f0\uae30"}, {"name": "Lv5", "title": "\ud0a4\ub77c\uc758 \ubc15\ubb3c\uad00 \uc5ec\ud589. 1, \ub8e8\ube0c\ub974 \ubc15\ubb3c\uad00(\ud504\ub791\uc2a4)", "library": "\uac15\ub3d9\uad6c\ub9bd\ud574\uacf5\ub3c4\uc11c\uad00", "in_date": "", "out_date": "2025.09.13", "status": "\ubc18\ub0a9\uc5f0\uae30"}, {"name": "Lv5", "title": "\ubcc4\uc744 \uc120\ubb3c\ud560\uac8c", "library": "\uac15\ub3d9\uad6c\ub9bd\ud574\uacf5\ub3c4\uc11c\uad00", "in_date": "", "out_date": "2025.09.13", "status": "\ubc18\ub0a9\uc5f0\uae30"}, {"name": "Lv5", "title": "\ub09c\uc7c1\uc774 \ud53c\ud130 : \uc778\uc0dd\uc744 \ubc14\uafbc \ubaa9\uc801\uc758 \ud798", "library": "\uac15\ub3d9\uad6c\ub9bd\ud574\uacf5\ub3c4\uc11c\uad00", "in_date": "", "out_date": "2025.09.13", "status": "\ubc18\ub0a9\uc5f0\uae30"}, {"name": "Lv5", "title": "\ud5dd\uac70 \uac8c\uc784", "library": "\uac15\ub3d9\uad6c\ub9bd\uc131\ub0b4\ub3c4\uc11c\uad00", "in_date": "", "out_date": "2025.09.07", "status": "\ubc18\ub0a9\uc5f0\uae30"}, {"name": "Lv5", "title": "\uc6b0\ud53c\uce58 \ubbf8\uc220\uad00", "library": "\uac15\ub3d9\uad6c\ub9bd\uc131\ub0b4\ub3c4\uc11c\uad00", "in_date": "", "out_date": "2025.09.07", "status": "\ubc18\ub0a9\uc5f0\uae30"}, {"name": "Lv5", "title": "\uc218\ubc15\ubc14 \uc11c\ub9ac \uc18c\ub3d9", "library": "\uac15\ub3d9\uad6c\ub9bd\uc131\ub0b4\ub3c4\uc11c\uad00", "in_date": "", "out_date": "2025.09.07", "status": "\ubc18\ub0a9\uc5f0\uae30"}, {"name": "Lv5", "title": "(\uc874\ub9ac\uc758)\uae08\uc735 \ubaa8\ud5d8\uc0dd \ud074\ub7fd. 1 : \ucc98\uc74c \ub9cc\ub098\ub294 \uae08\uc735\ub3d9\ud654", "library": "\uac15\ub3d9\uad6c\ub9bd\uc131\ub0b4\ub3c4\uc11c\uad00", "in_date": "", "out_date": "2025.09.07", "status": "\ubc18\ub0a9\uc5f0\uae30"}]